Workbook

Sheet SETTINGS
A1: ⚙ SETTINGS & REFERENCE DATA
A3: DO NOT MODIFY — Reference lists used by dropdowns and formulas across the workbook
A5: PRODUCTS — Foods Line (10) | E5: SOCIAL PLATFORMS | I5: AD / MEDIA PLATFORMS | M5: REPORTING MONTHS
A6: 1 | B6: Hemp Seed Oil 500ml | E6: 1 | F6: Instagram | I6: 1 | J6: Meta (Facebook/Instagram) | M6: 1 | N6: Jan-25
A7: 2 | B7: Hemp Protein Powder 1kg | E7: 2 | F7: Facebook | I7: 2 | J7: Google Ads | M7: 2 | N7: Feb-25
A8: 3 | B8: Hemp Hearts 500g | E8: 3 | F8: TikTok | I8: 3 | J8: TikTok Ads | M8: 3 | N8: Mar-25
A9: 4 | B9: Hemp Granola 400g | E9: 4 | F9: YouTube | I9: 4 | J9: YouTube Ads | M9: 4 | N9: Apr-25
A10: 5 | B10: Hemp Energy Bar (Box 12) | E10: 5 | F10: LinkedIn | I10: 5 | J10: Display/Programmatic | M10: 5 | N10: May-25
A11: 6 | B11: Hemp Superfood Blend 300g | E11: 6 | F11: Twitter/X | I11: 6 | J11: Influencer | M11: 6 | N11: Jun-25
A12: 7 | B12: Hemp Omega Capsules 60s | I12: 7 | J12: Other | M12: 7 | N12: Jul-25
A13: 8 | B13: Hemp Infused Honey 250g | M13: 8 | N13: Aug-25
A14: 9 | B14: Hemp Seed Butter 400g | M14: 9 | N14: Sep-25
A15: 10 | B15: Hemp Flour 1kg | M15: 10 | N15: Oct-25
M16: 11 | N16: Nov-25
M17: 12 | N17: Dec-25
E18: CAMPAIGN STATUSES | I18: CAMPAIGN OBJECTIVES | M18: 13 | N18: Jan-26
E19: 1 | F19: Planning | I19: 1 | J19: Brand Awareness | M19: 14 | N19: Feb-26
E20: 2 | F20: Active | I20: 2 | J20: Reach | M20: 15 | N20: Mar-26
E21: 3 | F21: Paused | I21: 3 | J21: Engagement | M21: 16 | N21: Apr-26
E22: 4 | F22: Completed | I22: 4 | J22: Website Traffic | M22: 17 | N22: May-26
E23: 5 | F23: Cancelled | I23: 5 | J23: Lead Generation | M23: 18 | N23: Jun-26
I24: 6 | J24: Product Launch | M24: 19 | N24: Jul-26
I25: 7 | J25: Seasonal Promo | M25: 20 | N25: Aug-26
I26: 8 | J26: Retargeting | M26: 21 | N26: Sep-26
M27: 22 | N27: Oct-26
M28: 23 | N28: Nov-26
M29: 24 | N29: Dec-26

Sheet DASHBOARD
A1: INVEGROW | Foods Line — Marketing Performance Dashboard
A2: Real-time marketing metrics overview. All figures pull automatically from data entry sheets.
A3: REPORTING MONTH: | I3: Jan-25 | J3: ◀ Select the month from dropdown to update all KPIs
A5: 🌐 WEBSITE & DIGITAL — data from Digital Analytics sheet
A6: SESSIONS | E6: UNIQUE VISITORS | I6: BOUNCE RATE % | M6: CONVERSION RATE %
A7: =IFERROR(SUMIF('Digital_Analytics'!$A:$A,$I$3,'Digital_Analytics'!$B:$B),"–") | E7: =IFERROR(SUMIF('Digital_Analytics'!$A:$A,$I$3,'Digital_Analytics'!$C:$C),"–") | I7: =IFERROR(AVERAGEIF('Digital_Analytics'!$A:$A,$I$3,'Digital_Analytics'!$E:$E),"–") | M7: =IFERROR(AVERAGEIF('Digital_Analytics'!$A:$A,$I$3,'Digital_Analytics'!$M:$M),"–")
A9: Monthly website sessions | E9: Unique users to site | I9: Lower is better | M9: Goal completions / sessions
A11: 📱 SOCIAL MEDIA — data from Social Media sheet
A12: TOTAL FOLLOWERS | E12: NEW FOLLOWERS | I12: TOTAL IMPRESSIONS | M12: AVG ENGAGEMENT RATE %
A13: =IFERROR(SUMIF('Social_Media'!$A:$A,$I$3,'Social_Media'!$C:$C),"–") | E13: =IFERROR(SUMIF('Social_Media'!$A:$A,$I$3,'Social_Media'!$D:$D),"–") | I13: =IFERROR(SUMIF('Social_Media'!$A:$A,$I$3,'Social_Media'!$F:$F),"–") | M13: =IFERROR(AVERAGEIF('Social_Media'!$A:$A,$I$3,'Social_Media'!$M:$M),"–")
A15: All platforms combined | E15: Net new this month | I15: All platforms | M15: Across platforms
A17: 💰 PAID ADVERTISING — data from Paid Ads sheet
A18: TOTAL AD SPEND (R) | E18: PAID IMPRESSIONS | I18: TOTAL PAID CLICKS | M18: PAID CONVERSIONS
A19: =IFERROR(SUMIF('Paid_Ads'!$A:$A,$I$3,'Paid_Ads'!$G:$G),"–") | E19: =IFERROR(SUMIF('Paid_Ads'!$A:$A,$I$3,'Paid_Ads'!$I:$I),"–") | I19: =IFERROR(SUMIF('Paid_Ads'!$A:$A,$I$3,'Paid_Ads'!$J:$J),"–") | M19: =IFERROR(SUMIF('Paid_Ads'!$A:$A,$I$3,'Paid_Ads'!$N:$N),"–")
A21: Actual spend this month | E21: All paid campaigns | I21: All paid campaigns | M21: Goal completions via ads
A23: 📧 EMAIL MARKETING — data from Email Mktg sheet
A24: EMAILS SENT | E24: AVG OPEN RATE % | I24: AVG CTR % | M24: AVG UNSUB RATE %
A25: =IFERROR(SUMIF('Email_Mktg'!$A:$A,$I$3,'Email_Mktg'!$D:$D),"–") | E25: =IFERROR(AVERAGEIF('Email_Mktg'!$A:$A,$I$3,'Email_Mktg'!$H:$H),"–") | I25: =IFERROR(AVERAGEIF('Email_Mktg'!$A:$A,$I$3,'Email_Mktg'!$J:$J),"–") | M25: =IFERROR(AVERAGEIF('Email_Mktg'!$A:$A,$I$3,'Email_Mktg'!$L:$L),"–")
A27: Total sends this month | E27: Benchmark: 20–25% | I27: Benchmark: 2–5% | M27: Benchmark: < 0.5%
A29: ✍ CONTENT & PR — data from Content & PR sheet
A30: CONTENT PIECES | E30: PR MENTIONS | I30: EARNED MEDIA VALUE (R) | M30: INFLUENCER REACH
A31: =IFERROR(SUMIF('Content_PR'!$A:$A,$I$3,'Content_PR'!$B:$B)+SUMIF('Content_PR'!$A:$A,$I$3,'Content_PR'!$C:$C)+SUMIF('Content_PR'!$A:$A,$I$3,'Content_PR'!$I:$I),"–") | E31: =IFERROR(SUMIF('Content_PR'!$A:$A,$I$3,'Content_PR'!$E:$E),"–") | I31: =IFERROR(SUMIF('Content_PR'!$A:$A,$I$3,'Content_PR'!$F:$F),"–") | M31: =IFERROR(SUMIF('Content_PR'!$A:$A,$I$3,'Content_PR'!$H:$H),"–")
A33: Blogs + social + videos | E33: Earned media coverage | I33: Equivalent paid value | M33: Combined influencer reach
A35: 🎯 CAMPAIGNS — data from Campaign Tracker sheet
A36: ACTIVE CAMPAIGNS | E36: TOTAL BUDGET (R) ALL CAMPAIGNS | I36: SPEND TO DATE (R) | M36: TOTAL LEADS / CONVERSIONS
A37: =IFERROR(COUNTIF('Campaigns'!$F:$F,"Active"),"–") | E37: =IFERROR(SUM('Campaigns'!$G:$G),"–") | I37: =IFERROR(SUM('Campaigns'!$H:$H),"–") | M37: =IFERROR(SUM('Campaigns'!$P:$P),"–")
A39: Currently running | E39: All campaigns total | I39: All campaigns total | M39: All campaigns total
A41: Invegrow Foods Line | Marketing Dashboard | Auto-updates from data entry sheets | Last updated: select month above

Sheet Digital_Analytics
A1: 🌐 DIGITAL ANALYTICS — Website & SEO Performance
A2: Monthly website performance data. Sources: Google Analytics / GA4, Google Search Console, CMS dashboards.
A3: INVEGROW | Foods Line Marketing | Bounce Rate & Conversion Rate: enter as a number e.g. 45.2 (meaning 45.2%) | Session Duration: minutes
A4: ⚡ Yellow cells = required entry. All traffic columns = number of sessions from that source. Totals row auto-calculates.
A5: PERIOD | B5: OVERALL TRAFFIC | E5: ENGAGEMENT | G5: TRAFFIC SOURCES | L5: CONVERSIONS | N5: MKTG CHANNEL NOTE | O5: NOTES
A6: MONTH | B6: SESSIONS | C6: UNIQUE VISITORS | D6: PAGE VIEWS | E6: BOUNCE RATE % | F6: AVG SESSION DURATION (min) | G6: ORGANIC TRAFFIC | H6: PAID TRAFFIC | I6: SOCIAL TRAFFIC | J6: DIRECT TRAFFIC | K6: OTHER TRAFFIC | L6: GOAL COMPLETIONS | M6: CONVERSION RATE % | N6: MAIN CHANNEL FOCUS THIS MONTH | O6: NOTES
A7: Jan-25
A8: Feb-25
A9: Mar-25
A10: Apr-25
A11: May-25
A12: Jun-25
A13: Jul-25
A14: Aug-25
A15: Sep-25
A16: Oct-25
A17: Nov-25
A18: Dec-25
... A30: Dec-26
A31: TOTALS / AVG | B31: =SUM(B7:B30) | C31: =SUM(C7:C30) | D31: =SUM(D7:D30) | E31: =IFERROR(AVERAGEIF(E7:E30,"<>"),"–") | F31: =IFERROR(AVERAGEIF(F7:F30,"<>"),"–") | G31: =SUM(G7:G30) | H31: =SUM(H7:H30) | I31: =SUM(I7:I30) | J31: =SUM(J7:J30) | K31: =SUM(K7:K30) | L31: =SUM(L7:L30) | M31: =IFERROR(AVERAGEIF(M7:M30,"<>"),"–")

Sheet Social_Media
A1: 📱 SOCIAL MEDIA — Platform Performance by Month
A2: One row per platform per month. Track each platform separately for accurate channel comparison.
A3: INVEGROW | Foods Line Marketing | Engagement Rate %: (Likes+Comments+Shares+Saves) ÷ Reach × 100 | Enter follower count at END of month
A4: ⚡ Select Month and Platform from dropdowns. Engagement Rate auto-calculates if you enter the component metrics.
A5: MONTH | B5: PLATFORM | C5: FOLLOWERS (END MO.) | D5: NEW FOLLOWERS | E5: POSTS PUBLISHED | F5: TOTAL IMPRESSIONS | G5: TOTAL REACH | H5: TOTAL ENGAGEMENTS | I5: LIKES | J5: COMMENTS | K5: SHARES | L5: SAVES | M5: ENGAGEMENT RATE % | N5: TOP PERFORMING CONTENT TYPE | O5: NOTES
A6: Jan-25 | B6: Instagram | M6: =IFERROR((I6+J6+K6+L6)/G6*100,"")
A7: Jan-25 | B7: Facebook | M7: =IFERROR((I7+J7+K7+L7)/G7*100,"")
A8: Jan-25 | B8: TikTok | M8: =IFERROR((I8+J8+K8+L8)/G8*100,"")
A9: Jan-25 | B9: YouTube | M9: =IFERROR((I9+J9+K9+L9)/G9*100,"")
A10: Jan-25 | B10: LinkedIn | M10: =IFERROR((I10+J10+K10+L10)/G10*100,"")
A11: Jan-25 | B11: Twitter/X | M11: =IFERROR((I11+J11+K11+L11)/G11*100,"")
A12: Feb-25 | B12: Instagram | M12: =IFERROR((I12+J12+K12+L12)/G12*100,"")
A13: Feb-25 | B13: Facebook | M13: =IFERROR((I13+J13+K13+L13)/G13*100,"")
A14: Feb-25 | B14: TikTok | M14: =IFERROR((I14+J14+K14+L14)/G14*100,"")
A15: Feb-25 | B15: YouTube | M15: =IFERROR((I15+J15+K15+L15)/G15*100,"")
A16: Feb-25 | B16: LinkedIn | M16: =IFERROR((I16+J16+K16+L16)/G16*100,"")
A17: Feb-25 | B17: Twitter/X | M17: =IFERROR((I17+J17+K17+L17)/G17*100,"")
... A149: Dec-26 | B149: Twitter/X | M149: =IFERROR((I149+J149+K149+L149)/G149*100,"")
A151: PLATFORM TOTALS (all months)
A152: Instagram | D152: =SUMIF(B6:B149,A152,D6:D149) | E152: =SUMIF(B6:B149,A152,E6:E149) | F152: =SUMIF(B6:B149,A152,F6:F149) | G152: =SUMIF(B6:B149,A152,G6:G149) | H152: =SUMIF(B6:B149,A152,H6:H149) | I152: =SUMIF(B6:B149,A152,I6:I149) | J152: =SUMIF(B6:B149,A152,J6:J149) | K152: =SUMIF(B6:B149,A152,K6:K149) | L152: =SUMIF(B6:B149,A152,L6:L149) | M152: =IFERROR(AVERAGEIF(B6:B149,A152,M6:M149),"–")
A153: Facebook | D153: =SUMIF(B6:B149,A153,D6:D149) | E153: =SUMIF(B6:B149,A153,E6:E149) | F153: =SUMIF(B6:B149,A153,F6:F149) | G153: =SUMIF(B6:B149,A153,G6:G149) | H153: =SUMIF(B6:B149,A153,H6:H149) | I153: =SUMIF(B6:B149,A153,I6:I149) | J153: =SUMIF(B6:B149,A153,J6:J149) | K153: =SUMIF(B6:B149,A153,K6:K149) | L153: =SUMIF(B6:B149,A153,L6:L149) | M153: =IFERROR(AVERAGEIF(B6:B149,A153,M6:M149),"–")
A154: TikTok | D154: =SUMIF(B6:B149,A154,D6:D149) | E154: =SUMIF(B6:B149,A154,E6:E149) | F154: =SUMIF(B6:B149,A154,F6:F149) | G154: =SUMIF(B6:B149,A154,G6:G149) | H154: =SUMIF(B6:B149,A154,H6:H149) | I154: =SUMIF(B6:B149,A154,I6:I149) | J154: =SUMIF(B6:B149,A154,J6:J149) | K154: =SUMIF(B6:B149,A154,K6:K149) | L154: =SUMIF(B6:B149,A154,L6:L149) | M154: =IFERROR(AVERAGEIF(B6:B149,A154,M6:M149),"–")
A155: YouTube | D155: =SUMIF(B6:B149,A155,D6:D149) | E155: =SUMIF(B6:B149,A155,E6:E149) | F155: =SUMIF(B6:B149,A155,F6:F149) | G155: =SUMIF(B6:B149,A155,G6:G149) | H155: =SUMIF(B6:B149,A155,H6:H149) | I155: =SUMIF(B6:B149,A155,I6:I149) | J155: =SUMIF(B6:B149,A155,J6:J149) | K155: =SUMIF(B6:B149,A155,K6:K149) | L155: =SUMIF(B6:B149,A155,L6:L149) | M155: =IFERROR(AVERAGEIF(B6:B149,A155,M6:M149),"–")
A156: LinkedIn | D156: =SUMIF(B6:B149,A156,D6:D149) | E156: =SUMIF(B6:B149,A156,E6:E149) | F156: =SUMIF(B6:B149,A156,F6:F149) | G156: =SUMIF(B6:B149,A156,G6:G149) | H156: =SUMIF(B6:B149,A156,H6:H149) | I156: =SUMIF(B6:B149,A156,I6:I149) | J156: =SUMIF(B6:B149,A156,J6:J149) | K156: =SUMIF(B6:B149,A156,K6:K149) | L156: =SUMIF(B6:B149,A156,L6:L149) | M156: =IFERROR(AVERAGEIF(B6:B149,A156,M6:M149),"–")
A157: Twitter/X | D157: =SUMIF(B6:B149,A157,D6:D149) | E157: =SUMIF(B6:B149,A157,E6:E149) | F157: =SUMIF(B6:B149,A157,F6:F149) | G157: =SUMIF(B6:B149,A157,G6:G149) | H157: =SUMIF(B6:B149,A157,H6:H149) | I157: =SUMIF(B6:B149,A157,I6:I149) | J157: =SUMIF(B6:B149,A157,J6:J149) | K157: =SUMIF(B6:B149,A157,K6:K149) | L157: =SUMIF(B6:B149,A157,L6:L149) | M157: =IFERROR(AVERAGEIF(B6:B149,A157,M6:M149),"–")

Sheet Paid_Ads
A1: 💰 PAID ADVERTISING — Campaign & Spend Tracker
A2: One row per campaign per month. Track spend, reach and performance for each paid media campaign.
A3: INVEGROW | Foods Line Marketing | All monetary values in ZAR (R) | CTR/ROAS auto-calculate from inputs
A4: ⚡ CTR % = Clicks ÷ Impressions × 100 | CPC = Spend ÷ Clicks | CPM = Spend ÷ Impressions × 1000 | ROAS = Revenue ÷ Spend
A5: MONTH | B5: CAMPAIGN NAME | C5: AD PLATFORM | D5: PRODUCT(S) PROMOTED | E5: CAMPAIGN OBJECTIVE | F5: BUDGET (R) | G5: ACTUAL SPEND (R) | H5: BUDGET UTILISATION % | I5: IMPRESSIONS | J5: CLICKS | K5: CTR % | L5: CPC (R) | M5: CPM (R) | N5: CONVERSIONS | O5: COST / CONV. (R) | P5: ROAS (Revenue/Spend) | Q5: NOTES
H6: =IFERROR(G6/F6*100,"") | K6: =IFERROR(J6/I6*100,"") | L6: =IFERROR(G6/J6,"") | M6: =IFERROR(G6/I6*1000,"") | O6: =IFERROR(G6/N6,"")
H7: =IFERROR(G7/F7*100,"") | K7: =IFERROR(J7/I7*100,"") | L7: =IFERROR(G7/J7,"") | M7: =IFERROR(G7/I7*1000,"") | O7: =IFERROR(G7/N7,"")
H8: =IFERROR(G8/F8*100,"") | K8: =IFERROR(J8/I8*100,"") | L8: =IFERROR(G8/J8,"") | M8: =IFERROR(G8/I8*1000,"") | O8: =IFERROR(G8/N8,"")
H9: =IFERROR(G9/F9*100,"") | K9: =IFERROR(J9/I9*100,"") | L9: =IFERROR(G9/J9,"") | M9: =IFERROR(G9/I9*1000,"") | O9: =IFERROR(G9/N9,"")
H10: =IFERROR(G10/F10*100,"") | K10: =IFERROR(J10/I10*100,"") | L10: =IFERROR(G10/J10,"") | M10: =IFERROR(G10/I10*1000,"") | O10: =IFERROR(G10/N10,"")
H11: =IFERROR(G11/F11*100,"") | K11: =IFERROR(J11/I11*100,"") | L11: =IFERROR(G11/J11,"") | M11: =IFERROR(G11/I11*1000,"") | O11: =IFERROR(G11/N11,"")
H12: =IFERROR(G12/F12*100,"") | K12: =IFERROR(J12/I12*100,"") | L12: =IFERROR(G12/J12,"") | M12: =IFERROR(G12/I12*1000,"") | O12: =IFERROR(G12/N12,"")
H13: =IFERROR(G13/F13*100,"") | K13: =IFERROR(J13/I13*100,"") | L13: =IFERROR(G13/J13,"") | M13: =IFERROR(G13/I13*1000,"") | O13: =IFERROR(G13/N13,"")
H14: =IFERROR(G14/F14*100,"") | K14: =IFERROR(J14/I14*100,"") | L14: =IFERROR(G14/J14,"") | M14: =IFERROR(G14/I14*1000,"") | O14: =IFERROR(G14/N14,"")
H15: =IFERROR(G15/F15*100,"") | K15: =IFERROR(J15/I15*100,"") | L15: =IFERROR(G15/J15,"") | M15: =IFERROR(G15/I15*1000,"") | O15: =IFERROR(G15/N15,"")
H16: =IFERROR(G16/F16*100,"") | K16: =IFERROR(J16/I16*100,"") | L16: =IFERROR(G16/J16,"") | M16: =IFERROR(G16/I16*1000,"") | O16: =IFERROR(G16/N16,"")
H17: =IFERROR(G17/F17*100,"") | K17: =IFERROR(J17/I17*100,"") | L17: =IFERROR(G17/J17,"") | M17: =IFERROR(G17/I17*1000,"") | O17: =IFERROR(G17/N17,"")
... H55: =IFERROR(G55/F55*100,"") | K55: =IFERROR(J55/I55*100,"") | L55: =IFERROR(G55/J55,"") | M55: =IFERROR(G55/I55*1000,"") | O55: =IFERROR(G55/N55,"")
A56: TOTALS | F56: =SUM(F6:F55) | G56: =SUM(G6:G55) | I56: =SUM(I6:I55) | J56: =SUM(J6:J55) | K56: =IFERROR(AVERAGEIF(K6:K55,"<>"),"–") | N56: =SUM(N6:N55) | P56: =IFERROR(AVERAGEIF(P6:P55,"<>"),"–")

Sheet Email_Mktg
A1: 📧 EMAIL MARKETING — Campaign Performance
A2: One row per email campaign. Track deliverability, open rates, click performance and list health.
A3: INVEGROW | Foods Line Marketing | Rates auto-calculate | Industry benchmarks: Open Rate 20–25% | CTR 2–5% | Unsub < 0.5%
A4: ⚡ Delivery Rate = Delivered ÷ Sent | Open Rate = Opens ÷ Delivered | CTR = Clicks ÷ Delivered
A5: MONTH | B5: CAMPAIGN NAME | C5: LIST SEGMENT | D5: EMAILS SENT | E5: DELIVERED | F5: DELIVERY RATE % | G5: OPENS | H5: OPEN RATE % | I5: CLICKS | J5: CLICK-THROUGH RATE % | K5: UNSUBSCRIBES | L5: UNSUB RATE % | M5: CONVERSIONS (if tracked) | N5: NOTES
F6: =IFERROR(E6/D6*100,"") | H6: =IFERROR(G6/E6*100,"") | J6: =IFERROR(I6/E6*100,"") | L6: =IFERROR(K6/E6*100,"")
F7: =IFERROR(E7/D7*100,"") | H7: =IFERROR(G7/E7*100,"") | J7: =IFERROR(I7/E7*100,"") | L7: =IFERROR(K7/E7*100,"")
F8: =IFERROR(E8/D8*100,"") | H8: =IFERROR(G8/E8*100,"") | J8: =IFERROR(I8/E8*100,"") | L8: =IFERROR(K8/E8*100,"")
F9: =IFERROR(E9/D9*100,"") | H9: =IFERROR(G9/E9*100,"") | J9: =IFERROR(I9/E9*100,"") | L9: =IFERROR(K9/E9*100,"")
F10: =IFERROR(E10/D10*100,"") | H10: =IFERROR(G10/E10*100,"") | J10: =IFERROR(I10/E10*100,"") | L10: =IFERROR(K10/E10*100,"")
F11: =IFERROR(E11/D11*100,"") | H11: =IFERROR(G11/E11*100,"") | J11: =IFERROR(I11/E11*100,"") | L11: =IFERROR(K11/E11*100,"")
F12: =IFERROR(E12/D12*100,"") | H12: =IFERROR(G12/E12*100,"") | J12: =IFERROR(I12/E12*100,"") | L12: =IFERROR(K12/E12*100,"")
F13: =IFERROR(E13/D13*100,"") | H13: =IFERROR(G13/E13*100,"") | J13: =IFERROR(I13/E13*100,"") | L13: =IFERROR(K13/E13*100,"")
F14: =IFERROR(E14/D14*100,"") | H14: =IFERROR(G14/E14*100,"") | J14: =IFERROR(I14/E14*100,"") | L14: =IFERROR(K14/E14*100,"")
F15: =IFERROR(E15/D15*100,"") | H15: =IFERROR(G15/E15*100,"") | J15: =IFERROR(I15/E15*100,"") | L15: =IFERROR(K15/E15*100,"")
F16: =IFERROR(E16/D16*100,"") | H16: =IFERROR(G16/E16*100,"") | J16: =IFERROR(I16/E16*100,"") | L16: =IFERROR(K16/E16*100,"")
F17: =IFERROR(E17/D17*100,"") | H17: =IFERROR(G17/E17*100,"") | J17: =IFERROR(I17/E17*100,"") | L17: =IFERROR(K17/E17*100,"")
... F55: =IFERROR(E55/D55*100,"") | H55: =IFERROR(G55/E55*100,"") | J55: =IFERROR(I55/E55*100,"") | L55: =IFERROR(K55/E55*100,"")
A56: TOTALS / AVERAGES | D56: =SUM(D6:D55) | E56: =SUM(E6:E55) | F56: =IFERROR(AVERAGEIF(F6:F55,"<>"),"–") | G56: =SUM(G6:G55) | H56: =IFERROR(AVERAGEIF(H6:H55,"<>"),"–") | I56: =SUM(I6:I55) | J56: =IFERROR(AVERAGEIF(J6:J55,"<>"),"–") | K56: =SUM(K6:K55) | L56: =IFERROR(AVERAGEIF(L6:L55,"<>"),"–") | M56: =SUM(M6:M55)

Sheet Content_PR
A1: ✍ CONTENT & PR — Organic Content & Earned Media
A2: Monthly content output and earned media tracking. Includes blog, press, influencer and video metrics.
A3: INVEGROW | Foods Line Marketing | Earned Media Value (EMV) in ZAR | Use CPM-equivalent formula if EMV not provided directly
A4: ⚡ PR Mentions = any media coverage (online/print/broadcast) | Influencer Reach = combined unique reach of all collabs that month
A5: MONTH | B5: BLOG / ARTICLES | C5: SOCIAL POSTS (org.) | D5: PRESS RELEASES | E5: PR MENTIONS | F5: EARNED MEDIA VAL (R) | G5: INFLUENCER COLLABS | H5: INFLUENCER COMB. REACH | I5: VIDEOS PUBLISHED | J5: VIDEO TOTAL VIEWS | K5: PODCAST FEATURES | L5: AVG REVIEW RATING /5 | M5: NOTES
A6: Jan-25
A7: Feb-25
A8: Mar-25
A9: Apr-25
A10: May-25
A11: Jun-25
A12: Jul-25
A13: Aug-25
A14: Sep-25
A15: Oct-25
A16: Nov-25
A17: Dec-25
... A29: Dec-26
A30: TOTALS / AVG | B30: =SUM(B6:B29) | C30: =SUM(C6:C29) | D30: =SUM(D6:D29) | E30: =SUM(E6:E29) | F30: =SUM(F6:F29) | G30: =SUM(G6:G29) | H30: =SUM(H6:H29) | I30: =SUM(I6:I29) | ... K30: =SUM(K6:K29) | L30: =IFERROR(AVERAGEIF(L6:L29,"<>"),"–")

Sheet Campaigns
A1: 🎯 CAMPAIGN TRACKER — End-to-End Campaign Record
A2: One row per campaign. Captures strategy, budget and results in a single view for learning and planning.
A3: INVEGROW | Foods Line Marketing | Budget Utilisation auto-calculates | Status dropdown controls row highlighting
A4: ⚡ Link campaign spend back to the Paid Ads sheet for full cost tracking | Add key learnings to improve future campaigns
A5: CAMPAIGN NAME | B5: OBJECTIVE | C5: PRODUCTS PROMOTED | D5: START DATE | E5: END DATE | F5: STATUS | G5: TOTAL BUDGET (R) | H5: SPEND TO DATE (R) | I5: BUDGET UTIL. % | J5: CHANNELS USED | K5: TARGET AUDIENCE | L5: KEY MESSAGE | M5: TOTAL IMPRESSIONS | N5: TOTAL REACH | O5: TOTAL ENGAGEMENTS | P5: LEADS / CONVERSIONS | Q5: KEY LEARNINGS
I6: =IFERROR(H6/G6*100,"")
I7: =IFERROR(H7/G7*100,"")
I8: =IFERROR(H8/G8*100,"")
I9: =IFERROR(H9/G9*100,"")
I10: =IFERROR(H10/G10*100,"")
I11: =IFERROR(H11/G11*100,"")
I12: =IFERROR(H12/G12*100,"")
I13: =IFERROR(H13/G13*100,"")
I14: =IFERROR(H14/G14*100,"")
I15: =IFERROR(H15/G15*100,"")
I16: =IFERROR(H16/G16*100,"")
I17: =IFERROR(H17/G17*100,"")
... I55: =IFERROR(H55/G55*100,"")

Sheet Product_Mktg
A1: 📦 PRODUCT MARKETING — Monthly Performance per Product
A2: One row per product per month. Track marketing investment and visibility for each of the 10 Foods Line SKUs.
A3: INVEGROW | Foods Line Marketing | All monetary values in ZAR (R) | Rating out of 5 | NPS: -100 to +100
A4: ⚡ Online Mentions = brand + product mentions across all channels | Link campaigns to Campaign Tracker sheet
A5: MONTH | B5: PRODUCT NAME | C5: MKTG BUDGET ALLOCATED (R) | D5: CHANNELS ACTIVATED | E5: CAMPAIGNS RAN | F5: TOTAL IMPRESSIONS | G5: TOTAL REACH | H5: TOTAL ENGAGEMENTS | I5: ONLINE MENTIONS | J5: CUSTOMER REVIEWS | K5: AVG REVIEW RATING /5 | L5: NPS SCORE | M5: ACTIVE PROMO? | N5: NOTES
A6: Jan-25 | B6: Hemp Seed Oil 500ml
A7: Jan-25 | B7: Hemp Protein Powder 1kg
A8: Jan-25 | B8: Hemp Hearts 500g
A9: Jan-25 | B9: Hemp Granola 400g
A10: Jan-25 | B10: Hemp Energy Bar (Box 12)
A11: Jan-25 | B11: Hemp Superfood Blend 300g
A12: Jan-25 | B12: Hemp Omega Capsules 60s
A13: Jan-25 | B13: Hemp Infused Honey 250g
A14: Jan-25 | B14: Hemp Seed Butter 400g
A15: Jan-25 | B15: Hemp Flour 1kg
A16: Feb-25 | B16: Hemp Seed Oil 500ml
A17: Feb-25 | B17: Hemp Protein Powder 1kg
... A245: Dec-26 | B245: Hemp Flour 1kg
A247: PRODUCT TOTALS (all months)
A248: All months | B248: Hemp Seed Oil 500ml | C248: =SUMIF(B6:B245,B248,C6:C245) | E248: =SUMIF(B6:B245,B248,E6:E245) | F248: =SUMIF(B6:B245,B248,F6:F245) | G248: =SUMIF(B6:B245,B248,G6:G245) | H248: =SUMIF(B6:B245,B248,H6:H245) | I248: =SUMIF(B6:B245,B248,I6:I245) | J248: =SUMIF(B6:B245,B248,J6:J245) | K248: =IFERROR(AVERAGEIF(B6:B245,B248,K6:K245),"–") | L248: =IFERROR(AVERAGEIF(B6:B245,B248,L6:L245),"–")
A249: All months | B249: Hemp Protein Powder 1kg | C249: =SUMIF(B6:B245,B249,C6:C245) | E249: =SUMIF(B6:B245,B249,E6:E245) | F249: =SUMIF(B6:B245,B249,F6:F245) | G249: =SUMIF(B6:B245,B249,G6:G245) | H249: =SUMIF(B6:B245,B249,H6:H245) | I249: =SUMIF(B6:B245,B249,I6:I245) | J249: =SUMIF(B6:B245,B249,J6:J245) | K249: =IFERROR(AVERAGEIF(B6:B245,B249,K6:K245),"–") | L249: =IFERROR(AVERAGEIF(B6:B245,B249,L6:L245),"–")
A250: All months | B250: Hemp Hearts 500g | C250: =SUMIF(B6:B245,B250,C6:C245) | E250: =SUMIF(B6:B245,B250,E6:E245) | F250: =SUMIF(B6:B245,B250,F6:F245) | G250: =SUMIF(B6:B245,B250,G6:G245) | H250: =SUMIF(B6:B245,B250,H6:H245) | I250: =SUMIF(B6:B245,B250,I6:I245) | J250: =SUMIF(B6:B245,B250,J6:J245) | K250: =IFERROR(AVERAGEIF(B6:B245,B250,K6:K245),"–") | L250: =IFERROR(AVERAGEIF(B6:B245,B250,L6:L245),"–")
A251: All months | B251: Hemp Granola 400g | C251: =SUMIF(B6:B245,B251,C6:C245) | E251: =SUMIF(B6:B245,B251,E6:E245) | F251: =SUMIF(B6:B245,B251,F6:F245) | G251: =SUMIF(B6:B245,B251,G6:G245) | H251: =SUMIF(B6:B245,B251,H6:H245) | I251: =SUMIF(B6:B245,B251,I6:I245) | J251: =SUMIF(B6:B245,B251,J6:J245) | K251: =IFERROR(AVERAGEIF(B6:B245,B251,K6:K245),"–") | L251: =IFERROR(AVERAGEIF(B6:B245,B251,L6:L245),"–")
A252: All months | B252: Hemp Energy Bar (Box 12) | C252: =SUMIF(B6:B245,B252,C6:C245) | E252: =SUMIF(B6:B245,B252,E6:E245) | F252: =SUMIF(B6:B245,B252,F6:F245) | G252: =SUMIF(B6:B245,B252,G6:G245) | H252: =SUMIF(B6:B245,B252,H6:H245) | I252: =SUMIF(B6:B245,B252,I6:I245) | J252: =SUMIF(B6:B245,B252,J6:J245) | K252: =IFERROR(AVERAGEIF(B6:B245,B252,K6:K245),"–") | L252: =IFERROR(AVERAGEIF(B6:B245,B252,L6:L245),"–")
A253: All months | B253: Hemp Superfood Blend 300g | C253: =SUMIF(B6:B245,B253,C6:C245) | E253: =SUMIF(B6:B245,B253,E6:E245) | F253: =SUMIF(B6:B245,B253,F6:F245) | G253: =SUMIF(B6:B245,B253,G6:G245) | H253: =SUMIF(B6:B245,B253,H6:H245) | I253: =SUMIF(B6:B245,B253,I6:I245) | J253: =SUMIF(B6:B245,B253,J6:J245) | K253: =IFERROR(AVERAGEIF(B6:B245,B253,K6:K245),"–") | L253: =IFERROR(AVERAGEIF(B6:B245,B253,L6:L245),"–")
A254: All months | B254: Hemp Omega Capsules 60s | C254: =SUMIF(B6:B245,B254,C6:C245) | E254: =SUMIF(B6:B245,B254,E6:E245) | F254: =SUMIF(B6:B245,B254,F6:F245) | G254: =SUMIF(B6:B245,B254,G6:G245) | H254: =SUMIF(B6:B245,B254,H6:H245) | I254: =SUMIF(B6:B245,B254,I6:I245) | J254: =SUMIF(B6:B245,B254,J6:J245) | K254: =IFERROR(AVERAGEIF(B6:B245,B254,K6:K245),"–") | L254: =IFERROR(AVERAGEIF(B6:B245,B254,L6:L245),"–")
A255: All months | B255: Hemp Infused Honey 250g | C255: =SUMIF(B6:B245,B255,C6:C245) | E255: =SUMIF(B6:B245,B255,E6:E245) | F255: =SUMIF(B6:B245,B255,F6:F245) | G255: =SUMIF(B6:B245,B255,G6:G245) | H255: =SUMIF(B6:B245,B255,H6:H245) | I255: =SUMIF(B6:B245,B255,I6:I245) | J255: =SUMIF(B6:B245,B255,J6:J245) | K255: =IFERROR(AVERAGEIF(B6:B245,B255,K6:K245),"–") | L255: =IFERROR(AVERAGEIF(B6:B245,B255,L6:L245),"–")
A256: All months | B256: Hemp Seed Butter 400g | C256: =SUMIF(B6:B245,B256,C6:C245) | E256: =SUMIF(B6:B245,B256,E6:E245) | F256: =SUMIF(B6:B245,B256,F6:F245) | G256: =SUMIF(B6:B245,B256,G6:G245) | H256: =SUMIF(B6:B245,B256,H6:H245) | I256: =SUMIF(B6:B245,B256,I6:I245) | J256: =SUMIF(B6:B245,B256,J6:J245) | K256: =IFERROR(AVERAGEIF(B6:B245,B256,K6:K245),"–") | L256: =IFERROR(AVERAGEIF(B6:B245,B256,L6:L245),"–")
A257: All months | B257: Hemp Flour 1kg | C257: =SUMIF(B6:B245,B257,C6:C245) | E257: =SUMIF(B6:B245,B257,E6:E245) | F257: =SUMIF(B6:B245,B257,F6:F245) | G257: =SUMIF(B6:B245,B257,G6:G245) | H257: =SUMIF(B6:B245,B257,H6:H245) | I257: =SUMIF(B6:B245,B257,I6:I245) | J257: =SUMIF(B6:B245,B257,J6:J245) | K257: =IFERROR(AVERAGEIF(B6:B245,B257,K6:K245),"–") | L257: =IFERROR(AVERAGEIF(B6:B245,B257,L6:L245),"–")
